Bank/__init__.py
Bank/accounts/__init__.py
Bank/accounts/account.py
Bank/accounts/chequing.py
Bank/accounts/saving.py
Bank/cards/__init__.py
Bank/cards/card.py
Bank/cards/credit.py
Bank/cards/debit.py
test_cards/__init__.py
test_cards/test_cards_base.py
test_cards/test_cards_credit.py
test_cards/test_cards_debit.py
Bank_Package_Aamir_and_Conrad-1.0.1.dist-info/LICENSE
Bank_Package_Aamir_and_Conrad-1.0.1.dist-info/METADATA
Bank_Package_Aamir_and_Conrad-1.0.1.dist-info/WHEEL
Bank_Package_Aamir_and_Conrad-1.0.1.dist-info/top_level.txt
Bank_Package_Aamir_and_Conrad-1.0.1.dist-info/RECORD
